pyque
