Metadata-Version: 1.0
Name: pyque
Version: 0.4.0
Summary: pythonic devops toolbelt
Home-page: https://github.com/bmaeser/pyque
Author: Bernhard Maeser
Author-email: bernhard.maeser@gmail.com
License: MIT
Platform: UNKNOWN
Classifier: Development Status :: 4 - Beta
Classifier: Topic :: Utilities
Classifier: Topic :: System :: Archiving :: Backup
Classifier: Topic :: System :: Systems Administration
Classifier: Operating System :: POSIX
Classifier: License :: OSI Approved :: MIT License
Classifier: Programming Language :: Python
Classifier: Programming Language :: Python :: 2.7
